do_artifactory/__init__.py
do_artifactory/do_artifactory.py
do_artifactory/specific_example.py
do_artifactory-0.0.8.data/data/share/do_artifactory/LICENSE
do_artifactory-0.0.8.data/data/share/do_artifactory/README.md
do_artifactory-0.0.8.data/data/share/do_artifactory/examples/ejemplo1.py
do_artifactory-0.0.8.dist-info/LICENSE
do_artifactory-0.0.8.dist-info/METADATA
do_artifactory-0.0.8.dist-info/WHEEL
do_artifactory-0.0.8.dist-info/entry_points.txt
do_artifactory-0.0.8.dist-info/top_level.txt
do_artifactory-0.0.8.dist-info/RECORD
