Metadata-Version: 2.1
Name: do-artifactory
Version: 0.0.8
Summary: Artifactory API
Home-page: https://gitlab.com/doberti/do_artifactory
Download-URL: http://pypi.python.org/pypi/do_artifactory/
Author: Daniel Oberti
Author-email: obertidaniel@gmail.com
License: MIT
Platform: any
Classifier: Programming Language :: Python :: 3
Classifier: License :: OSI Approved :: MIT License
Classifier: Operating System :: OS Independent
Requires-Python: >=3.7
License-File: LICENSE
Requires-Dist: dohq-artifactory
Requires-Dist: tabulate
Requires-Dist: redis
Requires-Dist: pandas
Requires-Dist: PyYAML
Requires-Dist: requests
Requires-Dist: urllib3
